formparse/__init__.py
formparse/formula.py
formparse-0.0.2.dist-info/LICENSE.txt
formparse-0.0.2.dist-info/METADATA
formparse-0.0.2.dist-info/WHEEL
formparse-0.0.2.dist-info/top_level.txt
formparse-0.0.2.dist-info/RECORD
