Metadata-Version: 2.1
Name: formparse
Version: 0.0.2
Summary: Simple library for evaluating mathematical formulas.
Home-page: https://github.com/nick28829/formparse
Author: Nicklas Bocksberger
Author-email: nicklas@bocksberger.com
License: MIT
Project-URL: Documentation, https://formparse.readthedocs.io/en/stable/
Project-URL: Source, https://github.com/nick28829/formparse
Project-URL: Tracker, https://github.com/nick28829/formparse/issues
Project-URL: Download, https://pypi.org/project/formparse/#files
Project-URL: Changelog, https://github.com/nick28829/formparse/CHANGELOG.rst
Platform: any
Classifier: Development Status :: 4 - Beta
Classifier: Programming Language :: Python
License-File: LICENSE.txt
Requires-Dist: importlib-metadata ; python_version < "3.8"
Provides-Extra: testing
Requires-Dist: setuptools ; extra == 'testing'
Requires-Dist: unittest ; extra == 'testing'
